HDF5_BLS/__init__.py
HDF5_BLS/analyze.py
HDF5_BLS/conversion_PSD.py
HDF5_BLS/errors.py
HDF5_BLS/load_data.py
HDF5_BLS/wrapper.py
HDF5_BLS/wrapper_compatibility.py
HDF5_BLS/brimfile_converter/__init__.py
HDF5_BLS/brimfile_converter/brim_converter.py
HDF5_BLS/brimfile_converter/hdf5_flattener.py
HDF5_BLS/load_formats/__init__.py
HDF5_BLS/load_formats/load_dat.py
HDF5_BLS/load_formats/load_errors.py
HDF5_BLS/load_formats/load_image.py
HDF5_BLS/load_formats/load_npy.py
HDF5_BLS/load_formats/load_sif.py
hdf5_bls-1.1.0.dist-info/METADATA
hdf5_bls-1.1.0.dist-info/WHEEL
hdf5_bls-1.1.0.dist-info/top_level.txt
hdf5_bls-1.1.0.dist-info/RECORD
