Metadata-Version: 2.4
Name: HDF5_BLS
Version: 1.1.0
Summary: A package to unify the storage of Brillouin Light Scattering related data in HDF5 files
Author-email: Pierre Bouvet <pierre.bouvet@meduniwien.ac.at>
License-Expression: GPL-3.0-or-later
Project-URL: Homepage, https://github.com/bio-brillouin/HDF5_BLS
Project-URL: Documentation, https://hdf5-bls.readthedocs.io/en/latest/
Project-URL: Issues, https://github.com/bio-brillouin/HDF5_BLS/issues
Keywords: HDF5,Brillouin,BLS
Classifier: Programming Language :: Python :: 3
Classifier: Operating System :: OS Independent
Requires-Python: >=3.6
Requires-Dist: h5py>=3.12
Requires-Dist: numpy>=2.0
Requires-Dist: Pillow>=10.0.1
Requires-Dist: scipy>=1.10
Requires-Dist: sif_parser>=0.3
Requires-Dist: openpyxl
Requires-Dist: pyperclip
Requires-Dist: pandas>=2.0.3
Requires-Dist: brimfile
Requires-Dist: matplotlib>=3.7.1
Provides-Extra: dev
Requires-Dist: pytest; extra == "dev"
Provides-Extra: docs
Requires-Dist: sphinx; extra == "docs"
Requires-Dist: sphinx-rtd-theme; extra == "docs"
